xretrieval/__init__.py
xretrieval/core.py
xretrieval/datasets_registry.py
xretrieval/metrics.py
xretrieval/models_registry.py
xretrieval/rrf.py
xretrieval/datasets/__init__.py
xretrieval/datasets/coco.py
xretrieval/models/__init__.py
xretrieval/models/base.py
xretrieval/models/blip2.py
xretrieval/models/bm25.py
xretrieval/models/sentence_transformers.py
xretrieval/models/timm.py
xretrieval-0.2.0.dist-info/METADATA
xretrieval-0.2.0.dist-info/WHEEL
xretrieval-0.2.0.dist-info/RECORD
