Metadata-Version: 2.3
Name: xretrieval
Version: 0.2.0
Summary: Retrieve and Evaluate with X(any) models
Project-URL: Homepage, https://github.com/dnth/x.retrieval
Project-URL: Bug Tracker, https://github.com/dnth/x.retrieval/issues
Author-email: Dickson Neoh <dickson.neoh@gmail.com>
License: MIT
Keywords: evaluation,machine-learning,multi-modal,retrieval
Classifier: Development Status :: 3 - Alpha
Classifier: Intended Audience :: Science/Research
Classifier: License :: OSI Approved :: MIT License
Classifier: Programming Language :: Python :: 3
Classifier: Programming Language :: Python :: 3.10
Classifier: Programming Language :: Python :: 3.11
Classifier: Programming Language :: Python :: 3.12
Classifier: Topic :: Scientific/Engineering :: Artificial Intelligence
Requires-Python: >=3.10
Requires-Dist: accelerate>=1.1.0
Requires-Dist: bm25s>=0.2.5
Requires-Dist: faiss-cpu>=1.9.0
Requires-Dist: loguru>=0.7.0
Requires-Dist: matplotlib>=3.9.0
Requires-Dist: pandas>=2.1.0
Requires-Dist: pillow>=11.0.0
Requires-Dist: pystemmer>=2.2.0.3
Requires-Dist: rich>=13.9.0
Requires-Dist: sentence-transformers>=3.3.0
Requires-Dist: timm>=1.0.0
Requires-Dist: torchmetrics>=1.6.0
Requires-Dist: tqdm>=4.67.0
Requires-Dist: transformers>=4.46.0
Provides-Extra: dev
Requires-Dist: black>=22.0; extra == 'dev'
Requires-Dist: flake8>=4.0; extra == 'dev'
Requires-Dist: isort>=5.0; extra == 'dev'
Requires-Dist: pytest>=7.0; extra == 'dev'
Provides-Extra: docs
Requires-Dist: ipykernel; extra == 'docs'
Requires-Dist: livereload; extra == 'docs'
Requires-Dist: mkdocs; extra == 'docs'
Requires-Dist: mkdocs-git-revision-date-localized-plugin; extra == 'docs'
Requires-Dist: mkdocs-git-revision-date-plugin; extra == 'docs'
Requires-Dist: mkdocs-jupyter>=0.24.0; extra == 'docs'
Requires-Dist: mkdocs-material>=9.1.3; extra == 'docs'
Requires-Dist: mkdocs-pdf-export-plugin; extra == 'docs'
Requires-Dist: mkdocstrings; extra == 'docs'
Requires-Dist: mkdocstrings-crystal; extra == 'docs'
Requires-Dist: mkdocstrings-python-legacy; extra == 'docs'
Requires-Dist: nbconvert; extra == 'docs'
Requires-Dist: nbformat; extra == 'docs'
Requires-Dist: pygments; extra == 'docs'
Requires-Dist: pymdown-extensions; extra == 'docs'
Requires-Dist: sphinx; extra == 'docs'
Requires-Dist: watchdog; extra == 'docs'
